textcanvas/__init__.py
textcanvas/charts.py
textcanvas/color.py
textcanvas/maths.py
textcanvas/textcanvas.py
textcanvas/utils.py
textcanvas-3.7.2.dist-info/licenses/LICENSE-APACHE
textcanvas-3.7.2.dist-info/licenses/LICENSE-MIT
textcanvas-3.7.2.dist-info/METADATA
textcanvas-3.7.2.dist-info/WHEEL
textcanvas-3.7.2.dist-info/top_level.txt
textcanvas-3.7.2.dist-info/RECORD
