Metadata-Version: 2.4
Name: textcanvas
Version: 3.7.2
Summary: Draw to the terminal like an HTML Canvas.
Author-email: Quentin Richert <noreply@richert.co>
License-Expression: MIT OR Apache-2.0
Project-URL: Homepage, https://github.com/qrichert/textcanvas
Keywords: tui,canvas,draw,terminal,console
Classifier: Programming Language :: Python :: 3
Classifier: Operating System :: OS Independent
Classifier: Intended Audience :: Developers
Requires-Python: >=3.12
License-File: LICENSE-MIT
License-File: LICENSE-APACHE
Requires-Dist: coverage>=7.6.12
Dynamic: license-file
